<?xml version="1.0" encoding="UTF-8"?>
<databaseChangeLog
        xmlns="http://www.liquibase.org/xml/ns/dbchangelog"
        xmlns:xsi="http://www.w3.org/2001/XMLSchema-instance"
        xsi:schemaLocation="http://www.liquibase.org/xml/ns/dbchangelog
                      http://www.liquibase.org/xml/ns/dbchangelog/dbchangelog-4.27.xsd"
        objectQuotingStrategy="QUOTE_ONLY_RESERVED_WORDS">
    <changeSet id="1768965082556-1" author="dinht">
        <createTable tableName="dc_option">
            <column autoIncrement="true" name="id" type="INT">
                <constraints nullable="false" primaryKey="true" primaryKeyName="pk_dc_option"/>
            </column>
            <column name="partner_code" type="VARCHAR(32)">
                <constraints nullable="false"/>
            </column>
            <column name="param_code" type="VARCHAR(256)">
                <constraints nullable="false"/>
            </column>
            <column name="param_value" type="VARCHAR(512)">
                <constraints nullable="false"/>
            </column>
        </createTable>
    </changeSet>

</databaseChangeLog>